boundaries/__init__.py
boundaries/admin.py
boundaries/base_views.py
boundaries/kml.py
boundaries/models.py
boundaries/titlecase.py
boundaries/urls.py
boundaries/views.py
boundaries/locale/en/LC_MESSAGES/django.mo
boundaries/locale/en/LC_MESSAGES/django.po
boundaries/management/__init__.py
boundaries/management/commands/__init__.py
boundaries/management/commands/analyzeshapefiles.py
boundaries/management/commands/compute_intersections.py
boundaries/management/commands/loadshapefiles.py
boundaries/migrations/0001_initial.py
boundaries/migrations/0002_auto_20141129_1402.py
boundaries/migrations/0003_auto_20150528_1338.py
boundaries/migrations/0004_auto_20150921_1607.py
boundaries/migrations/0005_auto_20150925_0338.py
boundaries/migrations/0006_switch_to_django_jsonfield.py
boundaries/migrations/0007_auto_20180325_1421.py
boundaries/migrations/0008_alter_boundary_extent_alter_boundary_metadata_and_more.py
boundaries/migrations/0009_alter_boundaryset_slug.py
boundaries/migrations/__init__.py
boundaries/static/js/jsonformatter.js
boundaries/templates/boundaries/apibrowser.html
boundaries/templates/boundaries/apidoc.html
boundaries/tests/__init__.py
boundaries/tests/test.py
boundaries/tests/test_boundary.py
boundaries/tests/test_boundary_detail.py
boundaries/tests/test_boundary_geo_detail.py
boundaries/tests/test_boundary_list.py
boundaries/tests/test_boundary_list_filter.py
boundaries/tests/test_boundary_list_geo.py
boundaries/tests/test_boundary_list_geo_filter.py
boundaries/tests/test_boundary_list_set.py
boundaries/tests/test_boundary_list_set_filter.py
boundaries/tests/test_boundary_list_set_geo.py
boundaries/tests/test_boundary_list_set_geo_filter.py
boundaries/tests/test_boundary_set.py
boundaries/tests/test_boundary_set_detail.py
boundaries/tests/test_boundary_set_list.py
boundaries/tests/test_boundary_set_list_filter.py
boundaries/tests/test_compute_intersections.py
boundaries/tests/test_definition.py
boundaries/tests/test_feature.py
represent_boundaries-0.10.2.dist-info/AUTHORS
represent_boundaries-0.10.2.dist-info/LICENSE
represent_boundaries-0.10.2.dist-info/METADATA
represent_boundaries-0.10.2.dist-info/WHEEL
represent_boundaries-0.10.2.dist-info/top_level.txt
represent_boundaries-0.10.2.dist-info/RECORD
