Metadata-Version: 2.1
Name: represent-boundaries
Version: 0.10.2
Summary: A web API to geographic boundaries loaded from shapefiles, packaged as a Django app.
Home-page: https://opennorth.github.io/represent-boundaries-docs/
Author: Open North Inc.
Author-email: represent@opennorth.ca
License: MIT
Classifier: Programming Language :: Python :: 3
Classifier: License :: OSI Approved :: MIT License
Classifier: Framework :: Django
Classifier: Topic :: Scientific/Engineering :: GIS
License-File: LICENSE
License-File: AUTHORS
Requires-Dist: django-appconf
Provides-Extra: test
Requires-Dist: coveralls ; extra == 'test'
Requires-Dist: testfixtures ; extra == 'test'
